setup.py
programaker_bridge/__init__.py
programaker_bridge/blocks.py
programaker_bridge/bridge.py
programaker_bridge/extra_data.py
programaker_bridge/protocol.py
programaker_bridge/registration.py
programaker_bridge/service_configuration.py
programaker_bridge/utils.py
programaker_bridge.egg-info/PKG-INFO
programaker_bridge.egg-info/SOURCES.txt
programaker_bridge.egg-info/dependency_links.txt
programaker_bridge.egg-info/requires.txt
programaker_bridge.egg-info/top_level.txt
programaker_bridge.egg-info/zip-safe
programaker_bridge/storage/__init__.py
programaker_bridge/storage/config.py
programaker_bridge/storage/flycheck_storage.py
programaker_bridge/storage/storage.py