Metadata-Version: 2.1
Name: programaker-bridge
Version: 0.0.4.dev14
Summary: Helper to build PrograMaker bridges.
Home-page: https://gitlab.com/programaker-project/bridges/programaker-python-lib
Author: kenkeiras
Author-email: kenkeiras@codigoparallevar.com
License: Apache License 2.0
Platform: UNKNOWN
Classifier: Programming Language :: Python :: 3
Classifier: License :: OSI Approved :: Apache Software License
Classifier: Operating System :: OS Independent
Classifier: Development Status :: 3 - Alpha
Classifier: Intended Audience :: Developers
Provides-Extra: storage
Provides-Extra: full
